{ "texts": [], "questions": [ { "id": 1, "topic": "I", "type": "normal", "question": "Qual é a capital de Portugal?", "options": ["Porto", "Lisboa", "Coimbra", "Todas as anteriores"], "correct": 1 }, { "id": 2, "topic": "I", "type": "normal", "question": "Qual é a língua oficial de Portugal?", "options": ["Espanhol", "Português", "Francês", "Todas as anteriores"], "correct": 1 }, { "id": 3, "topic": "I", "type": "normal", "question": "O Pico situa-se em que arquipélago?", "options": ["Madeira", "Açores", "Canárias", "Todas as anteriores"], "correct": 1 }, { "id": 4, "topic": "I", "type": "normal", "question": "Qual é o rio mais longo de Portugal?", "options": ["Douro", "Tejo", "Guadiana", "Todas as anteriores"], "correct": 1 }, { "id": 5, "topic": "I", "type": "normal", "question": "Portugal é um Estado:", "options": ["Federal", "Unitário", "Confederado", "Todas as anteriores"], "correct": 1 }, { "id": 6, "topic": "II", "type": "normal", "question": "Quem escreveu 'Os Lusíadas'?", "options": ["Fernando Pessoa", "Luís de Camões", "Eça de Queirós", "Todas as anteriores"], "correct": 1 }, { "id": 7, "topic": "II", "type": "normal", "question": "Qual é o planeta mais próximo do Sol?", "options": ["Vénus", "Mercúrio", "Marte", "Todas as anteriores"], "correct": 1 }, { "id": 8, "topic": "II", "type": "normal", "question": "Quem pintou a Mona Lisa?", "options": ["Michelangelo", "Leonardo da Vinci", "Rafael", "Todas as anteriores"], "correct": 1 }, { "id": 9, "topic": "II", "type": "normal", "question": "Qual é o oceano que banha Portugal?", "options": ["Atlântico", "Índico", "Pacífico", "Todas as anteriores"], "correct": 0 }, { "id": 10, "topic": "II", "type": "normal", "question": "Qual é a moeda do Japão?", "options": ["Yuan", "Won", "Iene", "Todas as anteriores"], "correct": 2 }, { "id": 11, "topic": "III", "type": "normal", "question": "Quantos Estados-membros tem a União Europeia (2024)?", "options": ["25", "26", "27", "Todas as anteriores"], "correct": 2 }, { "id": 12, "topic": "III", "type": "normal", "question": "Qual é a moeda oficial da maioria dos países da UE?", "options": ["Euro", "Libra", "Dólar", "Todas as anteriores"], "correct": 0 }, { "id": 13, "topic": "III", "type": "normal", "question": "O Parlamento Europeu é eleito por:", "options": ["Nomeação", "Sufrágio universal", "Concurso público", "Todas as anteriores"], "correct": 1 }, { "id": 14, "topic": "III", "type": "normal", "question": "A sede da Comissão Europeia situa-se em:", "options": ["Luxemburgo", "Estrasburgo", "Bruxelas", "Todas as anteriores"], "correct": 2 }, { "id": 15, "topic": "IV", "type": "normal", "question": "A Constituição da República Portuguesa foi aprovada em:", "options": ["1974", "1975", "1976", "Todas as anteriores"], "correct": 2 }, { "id": 16, "topic": "IV", "type": "normal", "question": "Portugal é um Estado de direito:", "options": ["Social", "Democrático", "Ambos", "Todas as anteriores"], "correct": 2 }, { "id": 17, "topic": "IV", "type": "normal", "question": "Quem exerce o poder legislativo?", "options": ["Governo", "Tribunais", "Assembleia da República", "Todas as anteriores"], "correct": 2 }, { "id": 18, "topic": "IV", "type": "normal", "question": "O Presidente da República é eleito por:", "options": ["Parlamento", "Governo", "Sufrágio universal", "Todas as anteriores"], "correct": 2 }, { "id": 19, "topic": "V", "type": "normal", "question": "A PSP é uma força de segurança de natureza:", "options": ["Militar", "Civil", "Privada", "Todas as anteriores"], "correct": 1 }, { "id": 20, "topic": "V", "type": "normal", "question": "A PSP depende de que ministério?", "options": ["Defesa", "Justiça", "Administração Interna", "Todas as anteriores"], "correct": 2 }, { "id": 21, "topic": "V", "type": "normal", "question": "Uma das missões da PSP é:", "options": ["Garantir a segurança interna", "Defender a legalidade democrática", "Proteger pessoas e bens", "Todas as anteriores"], "correct": 3 }, { "id": 22, "topic": "V", "type": "normal", "question": "A PSP atua preferencialmente em:", "options": ["Meio rural", "Zonas urbanas", "Fronteiras", "Todas as anteriores"], "correct": 1 }, { "id": 23, "topic": "VI", "type": "normal", "question": "Os Direitos Humanos são:", "options": ["Universais", "Indivisíveis", "Interdependentes", "Todas as anteriores"], "correct": 3 }, { "id": 24, "topic": "VI", "type": "normal", "question": "O direito à vida é:", "options": ["Relativo", "Fundamental", "Opcional", "Todas as anteriores"], "correct": 1 }, { "id": 25, "topic": "VI", "type": "normal", "question": "A tortura é:", "options": ["Permitida", "Limitada", "Proibida", "Todas as anteriores"], "correct": 2 }, { "id": 26, "topic": "VII", "type": "normal", "question": "Qual é o atual Secretário-Geral da ONU?", "options": ["Ban Ki-moon", "António Guterres", "Jens Stoltenberg", "Todas as anteriores"], "correct": 1 }, { "id": 27, "topic": "VII", "type": "normal", "question": "A NATO é uma organização de carácter:", "options": ["Económico", "Militar", "Cultural", "Todas as anteriores"], "correct": 1 } ]}